glad/__init__.py
glad/__main__.py
glad/opener.py
glad/parse.py
glad/spec.py
glad/util.py
glad/files/__init__.py
glad/files/egl.xml
glad/files/gl.xml
glad/files/glx.xml
glad/files/khrplatform.h
glad/files/wgl.xml
glad/lang/__init__.py
glad/lang/c/__init__.py
glad/lang/c/debug.py
glad/lang/c/generator.py
glad/lang/c/loader/__init__.py
glad/lang/c/loader/egl.py
glad/lang/c/loader/gl.py
glad/lang/c/loader/glx.py
glad/lang/c/loader/wgl.py
glad/lang/common/__init__.py
glad/lang/common/generator.py
glad/lang/common/loader.py
glad/lang/common/util.py
glad/lang/d/__init__.py
glad/lang/d/generator.py
glad/lang/d/loader/__init__.py
glad/lang/d/loader/egl.py
glad/lang/d/loader/gl.py
glad/lang/d/loader/glx.py
glad/lang/d/loader/wgl.py
glad/lang/nim/__init__.py
glad/lang/nim/generator.py
glad/lang/nim/loader/__init__.py
glad/lang/nim/loader/egl.py
glad/lang/nim/loader/gl.py
glad/lang/nim/loader/glx.py
glad/lang/nim/loader/wgl.py
glad/lang/pascal/__init__.py
glad/lang/pascal/generator.py
glad/lang/pascal/loader/__init__.py
glad/lang/pascal/loader/gl.py
glad/lang/volt/__init__.py
glad/lang/volt/generator.py
glad/lang/volt/loader/__init__.py
glad/lang/volt/loader/egl.py
glad/lang/volt/loader/gl.py
glad/lang/volt/loader/glx.py
glad/lang/volt/loader/wgl.py
glad-0.1.35.dist-info/LICENSE
glad-0.1.35.dist-info/METADATA
glad-0.1.35.dist-info/WHEEL
glad-0.1.35.dist-info/entry_points.txt
glad-0.1.35.dist-info/top_level.txt
glad-0.1.35.dist-info/RECORD
